{
  "hash": "59531945",
  "configHash": "7e2ae5d3",
  "lockfileHash": "453e67d1",
  "browserHash": "e2be7cc0",
  "optimized": {
    "vue": {
      "src": "../../../../node_modules/vue/dist/vue.runtime.esm-bundler.js",
      "file": "vue.js",
      "fileHash": "bda3a92e",
      "needsInterop": false
    },
    "vitepress > @vue/devtools-api": {
      "src": "../../../../node_modules/@vue/devtools-api/dist/index.js",
      "file": "vitepress___@vue_devtools-api.js",
      "fileHash": "734bb7de",
      "needsInterop": false
    },
    "vitepress > @vueuse/core": {
      "src": "../../../../node_modules/@vueuse/core/index.mjs",
      "file": "vitepress___@vueuse_core.js",
      "fileHash": "c051425a",
      "needsInterop": false
    },
    "vitepress > @vueuse/integrations/useFocusTrap": {
      "src": "../../../../node_modules/@vueuse/integrations/useFocusTrap.mjs",
      "file": "vitepress___@vueuse_integrations_useFocusTrap.js",
      "fileHash": "dff7cd4b",
      "needsInterop": false
    },
    "vitepress > mark.js/src/vanilla.js": {
      "src": "../../../../node_modules/mark.js/src/vanilla.js",
      "file": "vitepress___mark__js_src_vanilla__js.js",
      "fileHash": "6dbeef8d",
      "needsInterop": false
    },
    "vitepress > minisearch": {
      "src": "../../../../node_modules/minisearch/dist/es/index.js",
      "file": "vitepress___minisearch.js",
      "fileHash": "e139b5ba",
      "needsInterop": false
    },
    "vitepress-theme-teek": {
      "src": "../../../../node_modules/vitepress-theme-teek/es/index.mjs",
      "file": "vitepress-theme-teek.js",
      "fileHash": "9b534440",
      "needsInterop": false
    }
  },
  "chunks": {
    "chunk-KUBE56QH": {
      "file": "chunk-KUBE56QH.js"
    },
    "chunk-RWXOEYSZ": {
      "file": "chunk-RWXOEYSZ.js"
    },
    "chunk-PZ5AY32C": {
      "file": "chunk-PZ5AY32C.js"
    }
  }
}